odoo/addons/mis_builder_budget_operating_unit/README.rst
odoo/addons/mis_builder_budget_operating_unit/__init__.py
odoo/addons/mis_builder_budget_operating_unit/__manifest__.py
odoo/addons/mis_builder_budget_operating_unit/i18n/mis_builder_budget_operating_unit.pot
odoo/addons/mis_builder_budget_operating_unit/models/__init__.py
odoo/addons/mis_builder_budget_operating_unit/models/mis_budget_item.py
odoo/addons/mis_builder_budget_operating_unit/readme/CONTRIBUTORS.rst
odoo/addons/mis_builder_budget_operating_unit/readme/DESCRIPTION.rst
odoo/addons/mis_builder_budget_operating_unit/readme/USAGE.rst
odoo/addons/mis_builder_budget_operating_unit/static/description/icon.png
odoo/addons/mis_builder_budget_operating_unit/static/description/index.html
odoo/addons/mis_builder_budget_operating_unit/views/mis_builder_budget.xml
odoo13_addon_mis_builder_budget_operating_unit-13.0.1.0.1.dist-info/METADATA
odoo13_addon_mis_builder_budget_operating_unit-13.0.1.0.1.dist-info/WHEEL
odoo13_addon_mis_builder_budget_operating_unit-13.0.1.0.1.dist-info/top_level.txt
odoo13_addon_mis_builder_budget_operating_unit-13.0.1.0.1.dist-info/RECORD
